wikipedia_revisions.cpython-35m-x86_64-linux-gnu.so
wikipedia_revisions-0.0.3.dist-info/RECORD
wikipedia_revisions-0.0.3.dist-info/WHEEL
wikipedia_revisions-0.0.3.dist-info/METADATA
wikipedia_revisions-0.0.3.dist-info/top_level.txt
